sharepoint4py/__init__.py
sharepoint4py/errors.py
sharepoint4py/folder.py
sharepoint4py/list.py
sharepoint4py/list_dict.py
sharepoint4py/office365.py
sharepoint4py/request_helper.py
sharepoint4py/site.py
sharepoint4py/soap.py
sharepoint4py/version.py
sharepoint4py-0.1.1.dist-info/LICENSE.txt
sharepoint4py-0.1.1.dist-info/METADATA
sharepoint4py-0.1.1.dist-info/WHEEL
sharepoint4py-0.1.1.dist-info/top_level.txt
sharepoint4py-0.1.1.dist-info/RECORD
