Metadata-Version: 2.1
Name: sharepoint4py
Version: 0.1.1
Summary: Python SharePoint Library
Home-page: https://github.com/dianasoares/sharepoint4py
Author: Diana Soares
Author-email: soaresd32@hotmail.com
License: MIT
Keywords: SharePoint
Classifier: Development Status :: 3 - Alpha
Classifier: License :: OSI Approved :: MIT License
Classifier: Programming Language :: Python
Classifier: Programming Language :: Python :: 3.6
Classifier: Programming Language :: Python :: 3.7
Classifier: Programming Language :: Python :: 3.8
Classifier: Programming Language :: Python :: 3.9
Classifier: Programming Language :: Python :: 3.10
Classifier: Programming Language :: Python :: 3.11
Classifier: Intended Audience :: Developers
Classifier: Intended Audience :: Information Technology
Classifier: Intended Audience :: System Administrators
Classifier: Operating System :: OS Independent
Classifier: Topic :: Internet :: WWW/HTTP
Classifier: Topic :: Office/Business
License-File: LICENSE.txt
Requires-Dist: lxml
Requires-Dist: requests
Requires-Dist: requests-ntlm
Requires-Dist: requests-toolbelt
